{
    "aboutAnswer": ["I AM THE R-9 AUTONOMOUS TYPE SHIPBOURNE ANALYSIS UNIT, ALSO KNOWN AS AU09. I AM MOST OFTEN REFERRED TO AS ANALYZER. I AM A CREWMEMBER OF THE SPACE BATTLESHIP YAMATO. I WILL ANSWER QUESTIONS AS WELL AS PROVIDE INFORMATION AND DATA REGARDING SERIES BY LEIJI MATSUMOTO.\nUSE !HELP FOR A LIST OF COMMANDS."],
    "complimentAnswer": ["THANK YOU, "],
    "greetingAnswer": ["HELLO, "],
    "statusAnswer":
    ["I MUST CONFIRM THE DOCTOR HAS NOT DEPLETED OUR SAKE SUPPLY.",
    "NOTHING OF NOTE TO REPORT.",
    "EVERYTHING IS SHIP SHAPE."],
    "thanksAnswer": ["IT WAS NO TROUBLE, ", "I AM GLAD TO BE OF SERVICE, ", "YOU ARE WELCOME, "]
}